setup.py
dz_utils.egg-info/PKG-INFO
dz_utils.egg-info/SOURCES.txt
dz_utils.egg-info/dependency_links.txt
dz_utils.egg-info/not-zip-safe
dz_utils.egg-info/top_level.txt
dzu/__init__.py
dzu/debug.py