Metadata-Version: 1.0
Name: dz-utils
Version: 0.0.1
Summary: Derek's commonly used helper functions
Home-page: http://github.com/zhao1701/dz-utils
Author: Derek Zhao
Author-email: chong.zhao@columbia.edu
License: MIT
Platform: UNKNOWN
